hookt.py
hookt-0.1.5.dist-info/LICENSE
hookt-0.1.5.dist-info/WHEEL
hookt-0.1.5.dist-info/METADATA
hookt-0.1.5.dist-info/RECORD
